Workbook

Sheet Content Plan
A1: ID | B1: Status | C1: Phase | D1: Post date | E1: Pillar | F1: Format | G1: Title | H1: Hook overlay (frame 1) | I1: Hook line (caption) | J1: Mechanism / angle | K1: Visual metaphor | L1: Twist | M1: Payoff / takeaway | N1: Loop / bookend | O1: Length (s) | P1: Primary goal | Q1: Facts to verify | R1: Risk flag | S1: Music mood | T1: Notes
A2: V001 | B2: Produced | C2: 1 · Reach | D2: 2026-10-27 | E2: E · Dev & AI-life memes | F2: POV Meme | G2: POV: You asked AI to fix ONE bug | H2: POV: YOU ASKED AI TO FIX ONE BUG | I2: Just fix this ONE. | J2: Over-eager AI 'improves' everything it wasn't asked to | K2: Blocks of unrequested changes bury the bug | L2: Bug count 1 -> 47; the original bug is still there | M2: Every. Single. Time. | N2: Callback to 'ONE bug' | O2: 20 | P2: Shares | Q2: - | R2: - | S2: Playful comedic bounce: pizzicato/marimba, 120-130 BPM | T2: V001 · produced 20 Oct 2026 · out/ai-one-bug.mp4
A3: V002 | B3: Produced | C3: 1 · Reach | D3: 2026-10-28 | E3: A · Attention traps | F3: Mechanism Reveal | G3: Why you can't stop scrolling | H3: 2:47 AM. STILL SCROLLING. | I3: If you lose hours to your feed every night, one 2006 design decision is why. | J3: Infinite scroll removed the stopping cue; pull-to-refresh is a variable-reward slot machine | K3: NEXT PAGE button kicked away; phone becomes a slot machine | L3: Both inventors regret it | M3: Bring back a stopping point: phone in another room, app timers | N3: Sentence loop: 'But tonight, around…' -> 2:47 AM | O3: 36 | P3: Shares + Saves | Q3: Raskin infinite scroll 2006 + 200,000 lifetimes/day estimate; Brichter Guardian 2017 quote | R3: - | S3: Curious -> build -> reveal: lo-fi keys + marimba, 110-120 BPM | T3: V002 · produced 20 Oct 2026 · out/scroll-trap.mp4
A4: V003 | B4: Planned | C4: 1 · Reach | D4: 2026-10-29 | E4: A · Attention traps | F4: Number Reveal | G4: Your streak is a hostage | H4: DAY 247. DON'T BREAK IT. | I4: If you've ever opened an app just to save a streak, you've met loss aversion. | J4: Losses feel about twice as strong as equal gains, so a streak turns a habit into something to protect | K4: The streak flame on a leash dragging the figure | L4: Some apps sell 'freezes' to rescue the streak they taught you to fear losing | M4: Ask: do I want the habit or the number? | N4: Counter ticks to 248 | O4: 35 | P4: Shares | Q4: Loss aversion ratio (~2x, Kahneman & Tversky); current streak-freeze offers in popular apps | R4: - | S4: Rising pulse + riser into a big hit on the number, 120 BPM
A5: V004 | B5: Planned | C5: 1 · Reach | D5: 2026-10-30 | E5: B · Money brain in the AI era | F5: Versus Fight | G5: UPI made spending stop hurting | H5: CASH vs UPI | I5: UPI didn't make you spend more. It made spending stop hurting. | J5: Pain of paying: cash hurts, taps don't (payment decoupling) | K5: A wallet with a pain-meter that goes silent | L5: The friction you hated was protecting you | M5: Do a weekly UPI history check | N5: Meter flickers back to zero | O5: 35 | P5: Saves | Q5: Prelec & Loewenstein 1998; Raghubir & Srivastava 2008 (cash vs card) | R5: Finance-edu (SEBI: no tips/tickers, no live prices, add 'education, not advice') | S5: Fight energy: drums + brass stabs, 130 BPM
A6: V005 | B6: Planned | C6: 1 · Reach | D6: 2026-10-31 | E6: E · Dev & AI-life memes | F6: POV Meme | G6: POV: demo day | H6: IT WORKED 5 MINUTES AGO. | I6: POV: it worked on your machine five minutes ago. | J6: Demo effect | K6: Laptop on fire on stage | L6: It works again the second the demo ends | M6: Always record a backup demo | N6: Back on stage | O6: 18 | P6: Shares | Q6: None | R6: - | S6: Playful comedic bounce: pizzicato/marimba, 120-130 BPM
A7: V006 | B7: Planned | C7: 1 · Reach | D7: 2026-11-01 | E7: F · Origin stories with a twist | F7: Mini Origin Doc | G7: The first computer bug was a real bug | H7: FIRST ACTUAL CASE OF BUG BEING FOUND. | I7: The first computer 'bug' was an actual bug. Taped into a logbook. | J7: Origin of 'bug' in computing folklore | K7: A moth stuck in a giant relay machine | L7: Engineers said 'bug' before the moth; the moth made it famous | M7: Sequel callback to 'ONE bug' | N7: Moth flies off | O7: 40 | P7: Shares | Q7: 1947 Harvard Mark II logbook (Smithsonian); 'bug' usage predates it | R7: - | S7: Storybook documentary: piano + strings, 90-100 BPM
A8: V007 | B8: Planned | C8: 1 · Reach | D8: 2026-11-02 | E8: A · Attention traps | F8: Mechanism Reveal | G8: Why the next episode starts by itself | H8: YOU DIDN'T PRESS PLAY. | I8: You meant to watch one episode. A 5-second countdown decided the rest. | J8: Autoplay flips the default: stopping becomes the action, continuing is automatic (default effect) | K8: A conveyor belt drops episodes into the figure's lap | L8: The countdown isn't a timer, it's a nudge | M8: Turn autoplay off; decide the stop before you press play | N8: Ends on the countdown '5…' -> frame 1 | O8: 30 | P8: Shares | Q8: Netflix/YouTube autoplay countdown lengths; default effect (Johnson & Goldstein 2003) | R8: - | S8: Curious -> build -> reveal: lo-fi keys + marimba, 110-120 BPM
A9: V008 | B9: Planned | C9: 1 · Reach | D9: 2026-11-03 | E9: B · Money brain in the AI era | F9: Number Reveal | G9: You paid ₹150 to save ₹40 | H9: FREE DELIVERY ABOVE ₹199 | I9: You just spent ₹150 extra to save ₹40 on delivery. | J9: Zero-price effect: 'free' warps value judgments | K9: The figure stuffing a cart to clear a 'FREE' bar | L9: ‘Free’ is the most expensive word in the app | M9: Ask what you'd buy if delivery cost ₹0 anyway | N9: Cart refills | O9: 30 | P9: Shares | Q9: Shampanier, Mazar & Ariely 2007 (zero price effect); numbers are illustrative | R9: Finance-edu (SEBI: no tips/tickers, no live prices, add 'education, not advice') | S9: Rising pulse + riser into a big hit on the number, 120 BPM
A10: V009 | B10: Planned | C10: 1 · Reach | D10: 2026-11-04 | E10: C · How AI actually works | F10: POV Meme | G10: POV: the smartest AI can't count the r's in strawberry | H10: HOW MANY R's? | I10: POV: the smartest AI on earth can't count the r's in 'strawberry'. | J10: Tokenisation hides letters from the model | K10: The word chopped into Lego bricks | L10: It never saw the letters, only the chunks | M10: Ask it to spell first, then count | N10: Strawberry bounces back | O10: 20 | P10: Shares | Q10: Tokenisation of 'strawberry'; note newer models often get it right | R10: - | S10: Playful comedic bounce: pizzicato/marimba, 120-130 BPM
A11: V010 | B11: Planned | C11: 1 · Reach | D11: 2026-11-05 | E11: A · Attention traps | F11: Mechanism Reveal | G11: Why that notification dot is red | H11: WHY IS IT RED? | I11: That little red dot isn't decoration. It's a nag your brain can't ignore. | J11: Red signals urgency; an unread count is an open loop the brain wants closed (Zeigarnik effect) | K11: The dot grows into a fire alarm over the figure's head | L11: The count is designed to never really reach zero | M11: Turn off badge counts for anything that isn't a human | N11: Dot pops back at the end | O11: 30 | P11: Shares | Q11: Zeigarnik effect basics; keep colour claims general | R11: - | S11: Curious -> build -> reveal: lo-fi keys + marimba, 110-120 BPM
A12: V011 | B12: Planned | C12: 1 · Reach | D12: 2026-11-06 | E12: E · Dev & AI-life memes | F12: POV Meme | G12: POV: Friday 5 PM 'quick fix' | H12: JUST A QUICK FIX. | I12: POV: it's Friday at 5 PM and you say 'just a quick fix'. | J12: Friday deploys | K12: Dominoes falling into the weekend | L12: The fix was one line. The weekend was all of it. | M12: Don't deploy on Friday | N12: Clock hits 5 again | O12: 18 | P12: Shares | Q12: None | R12: - | S12: Playful comedic bounce: pizzicato/marimba, 120-130 BPM
A13: V012 | B13: Planned | C13: 1 · Reach | D13: 2026-11-07 | E13: B · Money brain in the AI era | F13: Mechanism Reveal | G13: Nobody buys the medium popcorn | H13: WHO BUYS THE MEDIUM? | I13: Nobody buys the medium popcorn. That's the point. | J13: Decoy effect: a bad middle option makes the expensive one look smart | K13: Three popcorn tubs; the middle one is a puppet on strings | L13: The option nobody picks is doing the selling | M13: Spot the decoy: compare the two you'd actually choose | N13: Puppet bows | O13: 35 | P13: Shares | Q13: Asymmetric dominance; Ariely's Economist subscription example | R13: Finance-edu (SEBI: no tips/tickers, no live prices, add 'education, not advice') | S13: Curious -> build -> reveal: lo-fi keys + marimba, 110-120 BPM
A14: V013 | B14: Planned | C14: 1 · Reach | D14: 2026-11-08 | E14: D · AI-era upgrade moves | F14: Myth vs Reality | G14: ‘AI won't take your job…’ | H14: AI WON'T TAKE YOUR JOB… | I14: ‘AI won't take your job, someone using AI will.’ Half true. | J14: The real edge is judgment: knowing what's good and what's wrong | K14: Two workers with AI; one checks, one copies | L14: Using AI is the easy part; checking it is the skill | M14: Practise reviewing AI output, not just generating it | N14: Boss walks in again | O14: 35 | P14: Shares | Q14: Avoid made-up stats; cite any job data used | R14: - | S14: Tension in minor, bright major release on the reality, 115 BPM
A15: V014 | B15: Planned | C15: 1 · Reach | D15: 2026-11-09 | E15: A · Attention traps | F15: Mechanism Reveal | G15: Why payment apps give you scratch cards | H15: ₹0. BETTER LUCK NEXT TIME. | I15: Why does a payment app hand you a scratch card that's usually empty? | J15: Variable rewards: rare, unpredictable wins keep you coming back to pay through the same app | K15: The scratch card grows into a mini slot machine | L15: The empty cards are part of the design, not a bug | M15: Notice the loop: pay for the thing, not for the scratch | N15: Scratch card reappears | O15: 30 | P15: Shares | Q15: How UPI app rewards/scratch cards work in India; variable-ratio schedules (Skinner); no odds claims | R15: - | S15: Curious -> build -> reveal: lo-fi keys + marimba, 110-120 BPM
... A101: V100 | B101: Planned | C101: 2 · Brand deals | D101: 2027-02-03 | E101: C · How AI actually works | F101: Number Reveal | G101: AI sees your photo as tiles | H101: 16 × 16 | I101: AI sees your photo as a grid of tiny tiles. | J101: Vision transformers split images into patches | K101: A photo cut into a mosaic, tiles talking to each other | L101: An image is treated like a sentence of tiles | M101: Clear, simple images get better AI answers | N101: Mosaic reassembles | O101: 35 | P101: Saves | Q101: Dosovitskiy et al. 2020 'An Image is Worth 16x16 Words' | R101: - | S101: Rising pulse + riser into a big hit on the number, 120 BPM

Sheet Summary
A1: Stickman Shorts: 100-video plan at a glance
A2: All counts are live formulas over the Content Plan tab.
A4: Pillar | B4: Description | C4: Phase 1 | D4: Phase 2 | E4: Total | F4: Share
A5: A · Attention traps | B5: Attention traps (how apps & AI hack your brain) | C5: =COUNTIFS('Content Plan'!$E$2:$E$101,A5,'Content Plan'!$C$2:$C$101,"1*") | D5: =COUNTIFS('Content Plan'!$E$2:$E$101,A5,'Content Plan'!$C$2:$C$101,"2*") | E5: =C5+D5 | F5: =IF(SUM($E$5:$E$10)=0,0,E5/SUM($E$5:$E$10))
A6: B · Money brain in the AI era | B6: Money brain in the AI era (behavioural money) | C6: =COUNTIFS('Content Plan'!$E$2:$E$101,A6,'Content Plan'!$C$2:$C$101,"1*") | D6: =COUNTIFS('Content Plan'!$E$2:$E$101,A6,'Content Plan'!$C$2:$C$101,"2*") | E6: =C6+D6 | F6: =IF(SUM($E$5:$E$10)=0,0,E6/SUM($E$5:$E$10))
A7: C · How AI actually works | B7: How AI actually works | C7: =COUNTIFS('Content Plan'!$E$2:$E$101,A7,'Content Plan'!$C$2:$C$101,"1*") | D7: =COUNTIFS('Content Plan'!$E$2:$E$101,A7,'Content Plan'!$C$2:$C$101,"2*") | E7: =C7+D7 | F7: =IF(SUM($E$5:$E$10)=0,0,E7/SUM($E$5:$E$10))
A8: D · AI-era upgrade moves | B8: AI-era upgrade moves | C8: =COUNTIFS('Content Plan'!$E$2:$E$101,A8,'Content Plan'!$C$2:$C$101,"1*") | D8: =COUNTIFS('Content Plan'!$E$2:$E$101,A8,'Content Plan'!$C$2:$C$101,"2*") | E8: =C8+D8 | F8: =IF(SUM($E$5:$E$10)=0,0,E8/SUM($E$5:$E$10))
A9: E · Dev & AI-life memes | B9: Dev & AI-life memes | C9: =COUNTIFS('Content Plan'!$E$2:$E$101,A9,'Content Plan'!$C$2:$C$101,"1*") | D9: =COUNTIFS('Content Plan'!$E$2:$E$101,A9,'Content Plan'!$C$2:$C$101,"2*") | E9: =C9+D9 | F9: =IF(SUM($E$5:$E$10)=0,0,E9/SUM($E$5:$E$10))
A10: F · Origin stories with a twist | B10: Origin stories with a twist | C10: =COUNTIFS('Content Plan'!$E$2:$E$101,A10,'Content Plan'!$C$2:$C$101,"1*") | D10: =COUNTIFS('Content Plan'!$E$2:$E$101,A10,'Content Plan'!$C$2:$C$101,"2*") | E10: =C10+D10 | F10: =IF(SUM($E$5:$E$10)=0,0,E10/SUM($E$5:$E$10))
A11: Total | C11: =SUM(C5:C10) | D11: =SUM(D5:D10) | E11: =SUM(E5:E10)
A13: Format | B13: Music mood | C13: Videos | D13: Avg length (s)
A14: Mechanism Reveal | B14: Curious -> build -> reveal: lo-fi keys + marimba, 110-120 BPM | C14: =COUNTIF('Content Plan'!$F$2:$F$101,A14) | D14: =IFERROR(AVERAGEIF('Content Plan'!$F$2:$F$101,A14,'Content Plan'!$O$2:$O$101),0)
A15: POV Meme | B15: Playful comedic bounce: pizzicato/marimba, 120-130 BPM | C15: =COUNTIF('Content Plan'!$F$2:$F$101,A15) | D15: =IFERROR(AVERAGEIF('Content Plan'!$F$2:$F$101,A15,'Content Plan'!$O$2:$O$101),0)
A16: Myth vs Reality | B16: Tension in minor, bright major release on the reality, 115 BPM | C16: =COUNTIF('Content Plan'!$F$2:$F$101,A16) | D16: =IFERROR(AVERAGEIF('Content Plan'!$F$2:$F$101,A16,'Content Plan'!$O$2:$O$101),0)
A17: Number Reveal | B17: Rising pulse + riser into a big hit on the number, 120 BPM | C17: =COUNTIF('Content Plan'!$F$2:$F$101,A17) | D17: =IFERROR(AVERAGEIF('Content Plan'!$F$2:$F$101,A17,'Content Plan'!$O$2:$O$101),0)
A18: Mini Origin Doc | B18: Storybook documentary: piano + strings, 90-100 BPM | C18: =COUNTIF('Content Plan'!$F$2:$F$101,A18) | D18: =IFERROR(AVERAGEIF('Content Plan'!$F$2:$F$101,A18,'Content Plan'!$O$2:$O$101),0)
A19: Versus Fight | B19: Fight energy: drums + brass stabs, 130 BPM | C19: =COUNTIF('Content Plan'!$F$2:$F$101,A19) | D19: =IFERROR(AVERAGEIF('Content Plan'!$F$2:$F$101,A19,'Content Plan'!$O$2:$O$101),0)
A21: Status | C21: Videos
A22: Produced | C22: =COUNTIF('Content Plan'!$B$2:$B$101,A22)
A23: Planned | C23: =COUNTIF('Content Plan'!$B$2:$B$101,A23)
A24: Scripted | C24: =COUNTIF('Content Plan'!$B$2:$B$101,A24)
A25: Rendered | C25: =COUNTIF('Content Plan'!$B$2:$B$101,A25)
A26: Posted | C26: =COUNTIF('Content Plan'!$B$2:$B$101,A26)
A27: Skipped | C27: =COUNTIF('Content Plan'!$B$2:$B$101,A27)
A30: Legend: yellow Status cells are the ones to update; green = already produced (V001, V002 example rows).

Sheet Production Rules
A1: Production rules (applied by every scheduled run)
A3: Positioning | B3: The Hidden Mechanism: how AI, money and your brain quietly work, explained with stick figures. Audience: people upgrading themselves with AI and money.
A4: Every video | B4: One invisible mechanism · one visual metaphor · one twist · one upgrade move · one CTA.
A5: Hook | B5: Three layers at 0:00: strong first frame (works muted) + text overlay + caption line. Write 5 hooks, score with youtube-agent-skill hookscore.py, ship only >= 55 (WORKABLE).
A6: Retention | B6: Visual change every 2-4 s (uneven); kinetic word captions; one 'wow' moment; loop or bookend ending; safe zone x 90-990, y 250-1500.
A7: Facts | B7: Verify every claim in 'Facts to verify' against a primary source before scripting; credit sources on screen when quoting; never invent numbers.
A8: Finance (SEBI) | B8: Education only: no buy/sell/hold calls, no tickers, no prices newer than 3 months, include 'education, not advice'. No paid deals with brokers/AMCs while unregistered.
A9: YouTube originality | B9: Rotate formats (never the same format back-to-back); unique angle, metaphor and music per video; human review before posting (July 2026 inauthentic-content rules).
A10: Real people | B10: Shown only as labelled generic figures; no AI likeness of real people discussing finance/health.
A11: Music | B11: Original MIDI score per video (music-gen + GeneralUser GS SoundFont), scenes start on bar lines; SFX synthesized (stickman-video).
A12: Delivery | B12: MP4 1080x1920 -> GitHub release; script/post copy -> Drive 'Videos' doc; update email -> Gmail thread 'Stickman Shorts — production updates'. Nothing is auto-posted.
